rosbags/image/__init__.py
rosbags/image/image.py
rosbags/image/py.typed
rosbags_image-0.10.3.dist-info/licenses/LICENSE.txt
rosbags_image-0.10.3.dist-info/METADATA
rosbags_image-0.10.3.dist-info/WHEEL
rosbags_image-0.10.3.dist-info/top_level.txt
rosbags_image-0.10.3.dist-info/RECORD
