Metadata-Version: 2.4
Name: rosbags-image
Version: 0.10.3
Summary: Pure Python library to convert ros image message data from and to opencv2.
Author-email: Ternaris <team@ternaris.com>
License-Expression: Apache-2.0
Project-URL: Homepage, https://gitlab.com/ternaris/rosbags-image
Project-URL: Documentation, https://ternaris.gitlab.io/rosbags-image
Project-URL: Source, https://gitlab.com/ternaris/rosbags-image
Project-URL: Issues, https://gitlab.com/ternaris/rosbags-image/issues
Project-URL: Changelog, https://gitlab.com/ternaris/rosbags-image/-/blob/master/CHANGES.rst
Keywords: conversion,cv_bridge,image,compressedimage,message,msg,opencv,ros,ros2,rosbag,rosbag1,rosbag2,rosbags
Classifier: Development Status :: 4 - Beta
Classifier: Programming Language :: Python
Classifier: Programming Language :: Python :: 3 :: Only
Classifier: Programming Language :: Python :: 3.10
Classifier: Programming Language :: Python :: 3.11
Classifier: Programming Language :: Python :: 3.12
Classifier: Programming Language :: Python :: 3.13
Classifier: Programming Language :: Python :: 3.14
Classifier: Topic :: Scientific/Engineering
Classifier: Typing :: Typed
Requires-Python: >=3.10
License-File: LICENSE.txt
Requires-Dist: numpy
Requires-Dist: rosbags>=0.9.20
Provides-Extra: opencv
Requires-Dist: opencv-python; extra == "opencv"
Provides-Extra: opencv-headless
Requires-Dist: opencv-python-headless; extra == "opencv-headless"
Dynamic: license-file
